setup.py
ij_discoverer.egg-info/PKG-INFO
ij_discoverer.egg-info/SOURCES.txt
ij_discoverer.egg-info/dependency_links.txt
ij_discoverer.egg-info/top_level.txt
intellij/__init__.py
intellij/discover/__init__.py