Metadata-Version: 1.0
Name: ij-discoverer
Version: 0.0.1
Summary: Library for IntelliJ IDE discovery and interaction
Home-page: UNKNOWN
Author: Alexander Kass
Author-email: UNKNOWN
License: MIT
Keywords: IntelliJ IDEA DataGrip PhpStorm PyCharm GoLand
Platform: UNKNOWN
